croaring/__init__.py
croaring/_roaring.abi3.so
croaring-0.0.2.dist-info/DESCRIPTION.rst
croaring-0.0.2.dist-info/METADATA
croaring-0.0.2.dist-info/RECORD
croaring-0.0.2.dist-info/WHEEL
croaring-0.0.2.dist-info/metadata.json
croaring-0.0.2.dist-info/top_level.txt
