Metadata-Version: 2.0
Name: croaring
Version: 0.0.2
Summary: Compressed integer sets based on Roaring bitmaps.
Home-page: https://github.com/zacharyvoase/croaring.py
Author: Zachary Voase
Author-email: zack@meat.io
License: UNLICENSE
Platform: UNKNOWN
Requires-Dist: cffi (>=1.4.0)
Requires-Dist: six (>=1.10.0)
